dbrownell_devtools_test2/EntryPoint.py
dbrownell_devtools_test2/Math.py
dbrownell_devtools_test2/__init__.py
dbrownell_devtools_test2-0.1.4.dist-info/LICENSE.txt
dbrownell_devtools_test2-0.1.4.dist-info/METADATA
dbrownell_devtools_test2-0.1.4.dist-info/WHEEL
dbrownell_devtools_test2-0.1.4.dist-info/entry_points.txt
dbrownell_devtools_test2-0.1.4.dist-info/top_level.txt
dbrownell_devtools_test2-0.1.4.dist-info/RECORD
